[
    {
        "timestamp": "2025-04-15 21:50:44",
        "task_name": "Decompose_Problem_Into_Subtasks",
        "task": "请委派一位学科专家，根据用户提出的问题：智慧医疗系统，提炼出其中核心的3-5个子问题，用中文回答。 每个子问题应明确、具体，并适合由不同学科专家进行深入分析，子问题之间具备关联性，总共构成解决整个大问题的基础。\n",
        "agent": "Crew Manager",
        "status": "started"
    },
    {
        "timestamp": "2025-04-15 21:52:13",
        "task_name": "Decompose_Problem_Into_Subtasks",
        "task": "请委派一位学科专家，根据用户提出的问题：智慧医疗系统，提炼出其中核心的3-5个子问题，用中文回答。 每个子问题应明确、具体，并适合由不同学科专家进行深入分析，子问题之间具备关联性，总共构成解决整个大问题的基础。\n",
        "agent": "Crew Manager",
        "status": "completed",
        "output": "1. **医疗数据标准化与整合**：如何实现多源异构医疗数据（如电子病历、影像数据、基因数据等）的统一标准化处理与高效整合，确保数据质量和互操作性？  \n2. **智能辅助诊断算法优化**：如何开发高精度、可解释的AI诊断模型（如基于深度学习的影像识别或自然语言处理的病历分析），并解决小样本、数据偏见等现实挑战？  \n3. **实时健康监测与预警**：如何通过物联网设备（如可穿戴设备）实现患者生理参数的实时采集，并构建动态风险预警模型以降低急症发生概率？  \n4. **个性化治疗推荐系统**：如何结合患者多维数据（病史、基因组、生活方式等）和临床指南，生成动态更新的个性化治疗方案，并平衡算法推荐与医生决策的关系？  \n5. **医疗资源分配与流程优化**：如何利用运筹学或强化学习技术优化医院内部资源（如床位、设备、人员）调度，以及区域医疗资源的均衡分配？  \n\n（注：每个子问题均涉及技术实现与跨学科协作，例如数据标准化需计算机科学与医学专家合作，而资源优化需联合管理学与AI团队。）"
    },
    {
        "timestamp": "2025-04-15 21:52:13",
        "task_name": "Subtask_MultiDomain_Expert_Analysis",
        "task": "请不同的学科专家，基于所在学科的专业知识，选择高度相关的多个子问题，进行全面深入的分析和解决，用中文回答。 给出的解决方案应足够专业，尽量具体、具备逻辑性。要求每个学科专家都进行回答，并且所有专家回答的问题集合能覆盖所有子问题。 当前主问题为：智慧医疗系统\n",
        "agent": "Crew Manager",
        "status": "started"
    }
]
